{
  "streams": [
    {
      "title": "My stream",
      "description": "Successful one",
      "id": 1
    },
    {
      "title": "Test Stream",
      "description": "Second one",
      "id": 2
    },
    {
      "title": "Authenticated ID",
      "description": "Getting the userId",
      "userId": "0101099917434619489392",
      "id": 3
    },
    {
      "title": "Test",
      "description": "1234567890",
      "userId": "0101099917434619489392",
      "id": 4
    },
    {
      "title": "Porgrammatic Redirection",
      "description": "YES!!",
      "userId": "101099917434619489392",
      "id": 5
    },
    {
      "title": "Refactoring Form",
      "description": "Reusing the form.",
      "userId": "101099917434619489392",
      "id": 6
    }
  ]
}